drf_pyjwt/__init__.py
drf_pyjwt/_stub_settings.py
drf_pyjwt/authentication.py
drf_pyjwt-0.0.8.dist-info/WHEEL
drf_pyjwt-0.0.8.dist-info/METADATA
drf_pyjwt-0.0.8.dist-info/RECORD
