Metadata-Version: 2.1
Name: drf_pyjwt
Version: 0.0.8
Summary: A JSON Web Token authentication extension for the Django REST Framework.
Home-page: https://github.com/vskrachkov/drf_pyjwt
Author: Vicheslav Krachkov
Author-email: vskrachkov@gmail.com
Requires-Python: >=3.8
Requires-Dist: pyjwt>=2.1,<3
Requires-Dist: django>=3.1
Requires-Dist: djangorestframework>=3.10
Requires-Dist: cryptography<4
